ga_scheduler/__init__.py
ga_scheduler/algorithm/__init__.py
ga_scheduler/algorithm/src.py
ga_scheduler/util/__init__.py
ga_scheduler/util/ecmoa.py
ga_scheduler/util/ga.py
ga_scheduler-2.7.8.dist-info/LICENSE
ga_scheduler-2.7.8.dist-info/METADATA
ga_scheduler-2.7.8.dist-info/WHEEL
ga_scheduler-2.7.8.dist-info/top_level.txt
ga_scheduler-2.7.8.dist-info/RECORD
