Metadata-Version: 2.1
Name: ga-scheduler
Version: 2.7.8
Summary: A Comprehensive Library for Solving Machine Scheduling Problems Using Genetic Algorithms
Home-page: https://github.com/Valdecy/ga_scheduler
Author: Valdecy Pereira
Author-email: valdecy.pereira@gmail.com
License: GNU
License-File: LICENSE
Requires-Dist: matplotlib
Requires-Dist: numpy
